modulomuysimple/__init__.py
modulomuysimple/resta.py
modulomuysimple/suma.py
modulomuysimple/extras/__init__.py
modulomuysimple/extras/divide.py
modulomuysimple/extras/multiplica.py
modulomuysimple-0.0.5.dist-info/METADATA
modulomuysimple-0.0.5.dist-info/WHEEL
modulomuysimple-0.0.5.dist-info/top_level.txt
modulomuysimple-0.0.5.dist-info/RECORD
