Metadata-Version: 2.1
Name: modulomuysimple
Version: 0.0.5
Summary: Mi primer paquete de Python
Author: Eduardo de Tena
Author-email: <tena15.eng@email.com>
Keywords: python,primer paquete
Classifier: Development Status :: 3 - Alpha
Classifier: Intended Audience :: Education
Classifier: Programming Language :: Python :: 2
Classifier: Programming Language :: Python :: 3
Classifier: Operating System :: MacOS :: MacOS X
Classifier: Operating System :: Microsoft :: Windows
